openur.py
openur/__init__.py
openur/cli.py
openur/config.py
openur/exceptions.py
openur/utils.py
openur/connections/__init__.py
openur/connections/connection_state.py
openur/connections/realTimeClient.py
openur/connections/robotConnector.py
openur/dashboard/__init__.py
openur/dashboard/dashboard.py
openur/kinematics/__init__.py
openur/kinematics/kinematic.py
openur/kinematics/manipulation.py
openur/rtde/__init__.py
openur/rtde/csv_binary_writer.py
openur/rtde/csv_reader.py
openur/rtde/csv_writer.py
openur/rtde/rtde.py
openur/rtde/rtde_config.py
openur/rtde/serialize.py
openur/rtde_command/__init__.py
openur/rtde_command/rtde_commands.py
openur/rtde_command/rtde_connect.py
openur/urscript/__init__.py
openur/urscript/urScript.py
openur/urscript/urScriptExt.py
openur/urscript/urscript1.py
openur/utils/__init__.py
openur/utils/dataLog.py
openur/utils/dataLogging.py
openur/utils/data_log.py
openur-0.3.0.dist-info/licenses/LICENSE
tests/__init__.py
tests/test_openur.py
openur-0.3.0.dist-info/METADATA
openur-0.3.0.dist-info/WHEEL
openur-0.3.0.dist-info/entry_points.txt
openur-0.3.0.dist-info/top_level.txt
openur-0.3.0.dist-info/RECORD
