Metadata-Version: 2.4
Name: OpenUr
Version: 0.3.0
Summary: All in one package for complete control of your UR robot.
Home-page: https://github.com/Jp-Beck
Author: Beck Isakov
Author-email: jp-beck@outlook.com
License: GNU GPLv3 License
Classifier: Programming Language :: Python :: 3
Classifier: Development Status :: 4 - Beta
Classifier: Intended Audience :: Developers
Classifier: Operating System :: OS Independent
Classifier: Topic :: System :: Hardware :: Hardware Drivers
Classifier: Topic :: Software Development :: Libraries :: Python Modules
Classifier: License :: OSI Approved :: GNU General Public License v3 (GPLv3)
Provides: openur
License-File: LICENSE
Requires-Dist: numpy
Requires-Dist: math3d
Dynamic: author
Dynamic: author-email
Dynamic: classifier
Dynamic: description
Dynamic: description-content-type
Dynamic: home-page
Dynamic: license
Dynamic: license-file
Dynamic: provides
Dynamic: requires-dist
Dynamic: summary
